clandestino_sqlite/__init__.py
clandestino_sqlite/infra.py
clandestino_sqlite/ref.py
clandestino_sqlite/repository.py
clandestino_sqlite-0.1.3.dist-info/LICENSE
clandestino_sqlite-0.1.3.dist-info/METADATA
clandestino_sqlite-0.1.3.dist-info/WHEEL
clandestino_sqlite-0.1.3.dist-info/RECORD
